nb_as_module/__init__.py
nb_as_module/colab.py
nb_as_module/nb_as_module.py
nb_as_module-0.2.2.dist-info/LICENSE
nb_as_module-0.2.2.dist-info/METADATA
nb_as_module-0.2.2.dist-info/WHEEL
nb_as_module-0.2.2.dist-info/top_level.txt
nb_as_module-0.2.2.dist-info/RECORD
