Metadata-Version: 2.1
Name: nb-as-module
Version: 0.2.2
Summary: Load a Jupyter Notebook as a module object.
Home-page: https://github.com/sradc/nb_as_module
Author: Sidney Radcliffe
Author-email: sidneyradcliffe@gmail.com
License: BSD
Platform: UNKNOWN
Classifier: Programming Language :: Python :: 3
Classifier: Operating System :: OS Independent
Requires-Python: >=3.6
Requires-Dist: IPython
Requires-Dist: nbformat
